synthetic_data_generators/__init__.py
synthetic_data_generators/time_series.py
synthetic_data_generators/utils/validators.py
synthetic_data_generators-1.3.0.dist-info/WHEEL
synthetic_data_generators-1.3.0.dist-info/METADATA
synthetic_data_generators-1.3.0.dist-info/RECORD
