Metadata-Version: 2.4
Name: synthetic-data-generators
Version: 1.3.0
Summary: Helper methods for generating synthetic data for testing and development.
Author: Chris Mahoney
Author-email: Chris Mahoney <synthetic-data-generators@data-science-extensions.com>
License-Expression: MIT
Classifier: Development Status :: 5 - Production/Stable
Classifier: License :: OSI Approved :: MIT License
Classifier: Topic :: Software Development :: Build Tools
Classifier: Topic :: Software Development :: Libraries :: Python Modules
Classifier: Topic :: Software Development :: Testing :: Unit
Classifier: Topic :: Utilities
Classifier: Programming Language :: Python :: 3
Classifier: Programming Language :: Python :: 3.10
Classifier: Programming Language :: Python :: 3.11
Classifier: Programming Language :: Python :: 3.12
Classifier: Programming Language :: Python :: 3.13
Classifier: Programming Language :: Python :: 3.14
Classifier: Intended Audience :: Developers
Requires-Dist: typeguard==4.*
Requires-Dist: more-itertools==10.*
Requires-Dist: pandas==2.*
Requires-Dist: numpy==2.*
Requires-Dist: toolbox-python>=1.3.2
Maintainer: Chris Mahoney
Maintainer-email: Chris Mahoney <synthetic-data-generators@data-science-extensions.com>
Requires-Python: >=3.10, <4.0
Project-URL: Changelog, https://github.com/data-science-extensions/synthetic-data-generators/releases
Project-URL: Documentation, https://data-science-extensions.com/synthetic-data-generators
Project-URL: Homepage, https://data-science-extensions.com/synthetic-data-generators
Project-URL: Issues, https://github.com/data-science-extensions/synthetic-data-generators/issues
Project-URL: Repository, https://github.com/data-science-extensions/synthetic-data-generators
